runmetricsvisualizer/__init__.py
runmetricsvisualizer/helpers.py
runmetricsvisualizer/plot.py
runmetricsvisualizer/runmetrics.py
runmetricsvisualizer/user_interface.py
runmetricsvisualizer-3.1.2.dist-info/LICENSE
runmetricsvisualizer-3.1.2.dist-info/METADATA
runmetricsvisualizer-3.1.2.dist-info/WHEEL
runmetricsvisualizer-3.1.2.dist-info/RECORD
