Metadata-Version: 2.1
Name: runmetricsvisualizer
Version: 3.1.2
Summary: A package for storing function runtime data and graphing it via GUI!
License: MIT
Author: Rahul Vikram
Requires-Python: >=3.9,<4.0
Classifier: License :: OSI Approved :: MIT License
Classifier: Programming Language :: Python :: 3
Classifier: Programming Language :: Python :: 3.9
Classifier: Programming Language :: Python :: 3.10
Classifier: Programming Language :: Python :: 3.11
Classifier: Programming Language :: Python :: 3.12
Requires-Dist: matplotlib (>=3.8.2,<4.0.0)
Requires-Dist: pandas (>=2.1.4,<3.0.0)
Requires-Dist: pillow (>=10.2.0,<11.0.0)
